CHANGES.txt
README.txt
bootstrap.py
buildout.cfg
setup.py
src/z3c/__init__.py
src/z3c.versionedresource.egg-info/PKG-INFO
src/z3c.versionedresource.egg-info/SOURCES.txt
src/z3c.versionedresource.egg-info/dependency_links.txt
src/z3c.versionedresource.egg-info/entry_points.txt
src/z3c.versionedresource.egg-info/namespace_packages.txt
src/z3c.versionedresource.egg-info/not-zip-safe
src/z3c.versionedresource.egg-info/requires.txt
src/z3c.versionedresource.egg-info/top_level.txt
src/z3c/versionedresource/README.txt
src/z3c/versionedresource/__init__.py
src/z3c/versionedresource/interfaces.py
src/z3c/versionedresource/list.py
src/z3c/versionedresource/meta.zcml
src/z3c/versionedresource/overrides.zcml
src/z3c/versionedresource/resource.py
src/z3c/versionedresource/version.py
src/z3c/versionedresource/zcml.py
src/z3c/versionedresource/tests/__init__.py
src/z3c/versionedresource/tests/simple.zcml
src/z3c/versionedresource/tests/test_doc.py
src/z3c/versionedresource/tests/testfiles/test.gif
src/z3c/versionedresource/tests/testfiles/test.pt
src/z3c/versionedresource/tests/testfiles/test.txt
src/z3c/versionedresource/tests/testfiles/subdir/test.gif
src/z3c/versionedresource/tests/testfiles/subdir/subsubdir/subtest.gif